<info>
<poster>[COLOR limegreen]MancMan[/COLOR] [COLOR orange] Batfink [/COLOR]</poster>
<thumbnail></thumbnail>
<fanart></fanart>
<info>


<dir>
<name>[B]Kids Movies[/B]</name>
<thumbnail></thumbnail>
<fanart></fanart>
<link>http://is.gd/RiSDwZ</link>
</dir>

####War Movies Dir#####
<dir>
<name>[B]War Movies[/B]</name>
<thumbnail></thumbnail>
<fanart></fanart>
<link>http://is.gd/Z7Tc4K</link>
</dir>

########Bond Movies########
<dir>
<name>[B]Bond Movies[/B]</name>
<thumbnail>http://johnrieber.files.wordpress.com/2013/06/james_bond_007.jpg</thumbnail>
<fanart>http://johnrieber.files.wordpress.com/2013/06/james_bond_007.jpg</fanart>
<link>http://pastebin.com/raw.php?i=tvszychK</link>
</dir>

<dir>
<name>[B]Superhero Movies[/B]</name>
<thumbnail>http://cdn3-www.craveonline.com/assets/uploads/2013/07/Superheroes.jpg</thumbnail>
<fanart>http://cdn3-www.craveonline.com/assets/uploads/2013/07/Superheroes.jpg</fanart>
<link>http://is.gd/8d3BT7</link>
</dir>



#####27/7 TV Shows#####
<dir>
<name>[B]24/7 TV Shows[/B]</name>
<thumbnail></thumbnail>
<fanart></fanart>
<link>http://is.gd/yuj1oI</link>
</dir>

#####TV Shows#####
<dir>
<name>[B]TV Shows[/B]</name>
<thumbnail></thumbnail>
<fanart></fanart>
<link>http://is.gd/NnKogJ</link>
</dir>









